aind_codeocean_utils/__init__.py
aind_codeocean_utils/api_handler.py
aind_codeocean_utils-1.0.0.dist-info/licenses/LICENSE
aind_codeocean_utils-1.0.0.dist-info/METADATA
aind_codeocean_utils-1.0.0.dist-info/WHEEL
aind_codeocean_utils-1.0.0.dist-info/top_level.txt
aind_codeocean_utils-1.0.0.dist-info/RECORD
